lgblkb_tools/__init__.py
lgblkb_tools/__main__.py
lgblkb_tools/common/__init__.py
lgblkb_tools/common/proxies.py
lgblkb_tools/common/utils.py
lgblkb_tools/db/__init__.py
lgblkb_tools/db/db_management.py
lgblkb_tools/db/sqla_orms.py
lgblkb_tools/gdal_datasets.py
lgblkb_tools/geometry/__init__.py
lgblkb_tools/geometry/field_utils.py
lgblkb_tools/geometry/line_utils.py
lgblkb_tools/geometry/point_utils.py
lgblkb_tools/geometry/poly_utils.py
lgblkb_tools/geometry/spatial_manager.py
lgblkb_tools/geometry/utils/__init__.py
lgblkb_tools/geometry/utils/geom_utils.py
lgblkb_tools/geometry/utils/katana.py
lgblkb_tools/geometry/utils/plot_utils.py
lgblkb_tools/geometry/utils/tsp.py
lgblkb_tools/logify.py
lgblkb_tools/pathify.py
lgblkb_tools/telegram_notify.py
lgblkb_tools/vectorize.py
lgblkb_tools/visualize.py
lgblkb_tools-2.1.0.dist-info/LICENSE
lgblkb_tools-2.1.0.dist-info/WHEEL
lgblkb_tools-2.1.0.dist-info/METADATA
lgblkb_tools-2.1.0.dist-info/RECORD
